pdpy11/__init__.py
pdpy11/__main__.py
pdpy11/_cli.py
pdpy11/architecture.py
pdpy11/bk_encoding.py
pdpy11/bk_wav.py
pdpy11/builtins.py
pdpy11/cli.py
pdpy11/compiler.py
pdpy11/containers.py
pdpy11/context.py
pdpy11/deferred.py
pdpy11/devices.py
pdpy11/formats.py
pdpy11/insns.py
pdpy11/metacommand_impl.py
pdpy11/metacommands.py
pdpy11/native.py
pdpy11/operators.py
pdpy11/parser.py
pdpy11/radix50.py
pdpy11/reports.py
pdpy11/types.py
pdpy11/version.py
pdpy11-2.0.4.dist-info/LICENSE
pdpy11-2.0.4.dist-info/METADATA
pdpy11-2.0.4.dist-info/WHEEL
pdpy11-2.0.4.dist-info/entry_points.txt
pdpy11-2.0.4.dist-info/top_level.txt
pdpy11-2.0.4.dist-info/RECORD
