Metadata-Version: 2.1
Name: pdpy11
Version: 2.0.4
Summary: Cross-platform assembler for PDP-11
Home-page: https://github.com/pdpy11/pdpy11
Author: Ivanq
Author-email: imachug@gmail.com
Project-URL: Bug Tracker, https://github.com/pdpy11/pdpy11/issues
Classifier: Programming Language :: Python :: 3
Classifier: Development Status :: 4 - Beta
Classifier: Environment :: Console
Classifier: Intended Audience :: Developers
Classifier: License :: OSI Approved :: GNU General Public License v3 or later (GPLv3+)
Classifier: License :: OSI Approved :: MIT License
Classifier: Operating System :: OS Independent
Classifier: Programming Language :: Assembly
Classifier: Programming Language :: Python :: 3.6
Classifier: Programming Language :: Python :: 3.7
Classifier: Programming Language :: Python :: 3.8
Classifier: Programming Language :: Python :: 3.9
Classifier: Programming Language :: Python :: 3.10
Classifier: Topic :: Software Development :: Assemblers
Requires-Python: >=3.6
License-File: LICENSE
